LICENSE
MANIFEST.in
README.md
setup.py
src/wheezy/__init__.py
src/wheezy.http.egg-info/PKG-INFO
src/wheezy.http.egg-info/SOURCES.txt
src/wheezy.http.egg-info/dependency_links.txt
src/wheezy.http.egg-info/namespace_packages.txt
src/wheezy.http.egg-info/not-zip-safe
src/wheezy.http.egg-info/requires.txt
src/wheezy.http.egg-info/top_level.txt
src/wheezy/http/__init__.py
src/wheezy/http/_cgi.py
src/wheezy/http/application.py
src/wheezy/http/authorization.py
src/wheezy/http/cache.py
src/wheezy/http/cachepolicy.py
src/wheezy/http/cacheprofile.py
src/wheezy/http/config.py
src/wheezy/http/cookie.py
src/wheezy/http/functional.py
src/wheezy/http/method.py
src/wheezy/http/middleware.py
src/wheezy/http/parse.py
src/wheezy/http/request.py
src/wheezy/http/response.py
src/wheezy/http/transforms.py